llmcomp/__init__.py
llmcomp/config.py
llmcomp/default_adapters.py
llmcomp/utils.py
llmcomp/finetuning/__init__.py
llmcomp/finetuning/manager.py
llmcomp/finetuning/update_jobs.py
llmcomp/finetuning/validation.py
llmcomp/question/judge.py
llmcomp/question/plots.py
llmcomp/question/question.py
llmcomp/question/result.py
llmcomp/question/viewer.py
llmcomp/runner/chat_completion.py
llmcomp/runner/model_adapter.py
llmcomp/runner/runner.py
llmcomp-1.3.1.dist-info/METADATA
llmcomp-1.3.1.dist-info/WHEEL
llmcomp-1.3.1.dist-info/entry_points.txt
llmcomp-1.3.1.dist-info/licenses/LICENSE
llmcomp-1.3.1.dist-info/RECORD
