Metadata-Version: 2.4
Name: llmcomp
Version: 1.3.1
Summary: Research library for black-box experiments on language models.
Project-URL: Homepage, https://github.com/johny-b/llmcomp
Project-URL: Repository, https://github.com/johny-b/llmcomp
Author-email: Jan Betley <jan.betley@gmail.com>
License: MIT
License-File: LICENSE
Requires-Python: >=3.9
Requires-Dist: backoff
Requires-Dist: filelock
Requires-Dist: matplotlib
Requires-Dist: numpy
Requires-Dist: openai>=1.0.0
Requires-Dist: pandas
Requires-Dist: pyyaml
Requires-Dist: requests
Requires-Dist: streamlit>=1.20.0
Requires-Dist: tqdm
